setup.py
awssh/__init__.py
awssh.egg-info/PKG-INFO
awssh.egg-info/SOURCES.txt
awssh.egg-info/dependency_links.txt
awssh.egg-info/requires.txt
awssh.egg-info/top_level.txt
bin/awssh-config