Metadata-Version: 1.0
Name: awssh
Version: 0.1
Summary: AWS SSH Config Helpr
Home-page: http://github.com/seomoz/awssh
Author: Dan Lecocq
Author-email: dan@seomoz.org
License: SEOmoz
Platform: Posix; MacOS X
Classifier: Development Status :: 3 - Alpha
Classifier: Environment :: Console
Classifier: Intended Audience :: Developers
Classifier: Topic :: System :: Shells
